{
  "configurations": [
    {
      "browse": {
        "databaseFilename": "${default}",
        "limitSymbolsToIncludedHeaders": false
      },
      "includePath": [
        "/opt/ros/jazzy/include/**",
        "/home/robomop/robomop_ws/src/robomop_navigation/include/**",
        "/home/robomop/robomop_ws/src/robomop_simulator/include/**",
        "/usr/include/**"
      ],
      "name": "ROS",
      "intelliSenseMode": "gcc-arm64",
      "compilerPath": "/usr/bin/gcc",
      "cStandard": "gnu11",
      "cppStandard": "c++14"
    }
  ],
  "version": 4
}